Metadata-Version: 2.1
Name: pythonrepoautomation
Version: 0.2
Summary: Description to build projects on Python language
Home-page: https://github.com/MarqQ/pythonrepoautomation
Author: Marcos Queiroz
Author-email: marcos.w.queiroz@gmail.com
License:                     GNU AFFERO GENERAL PUBLIC LICENSE
